{
  "number": "H1390",
  "language": "hebrew",
  "transliteration": "Gibʻâh",
  "pronunciation": "ghib-aw'",
  "definition": "Gibah; the name of three places in Palestine",
  "kjvTranslation": "Gibeah, the hill.",
  "translations": {
    "bg": "Гиба; името на три места в Палестина",
    "cs": "Giba; název tří míst v Palestině",
    "da": "Gibah; navnet på tre steder i Palæstina",
    "de": "Gibah; der Name von drei Orten in Palästina",
    "el": "Γίμπα, το όνομα τριών τόπων στην Παλαιστίνη",
    "es": "Gibah; nombre de tres lugares de Palestina",
    "et": "Gibah; kolme Palestiinas asuva koha nimi",
    "fi": "Gibah; kolmen paikan nimi Palestiinassa",
    "fr": "Gibah, nom de trois localités en Palestine",
    "hu": "Gibah; három palesztinai helység neve",
    "id": "Gibah; nama tiga tempat di Palestina",
    "it": "Gibah; il nome di tre località della Palestina",
    "ja": "ギバ；パレスチナの3つの地名",
    "ko": "기바; 팔레스타인의 세 곳의 이름",
    "lt": "Giba; trijų vietovių Palestinoje pavadinimas",
    "lv": "Gibah; trīs vietu nosaukums Palestīnā",
    "nb": "Gibah; navnet på tre steder i Palestina",
    "nl": "Gibah; de naam van drie plaatsen in Palestina",
    "pl": "Gibah; nazwa trzech miejsc w Palestynie",
    "pt": "Gibá; nome de três lugares na Palestina",
    "ro": "Gibah; numele a trei locuri din Palestina",
    "ru": "Гибах; название трех мест в Палестине",
    "sk": "Giba; názov troch miest v Palestíne",
    "sl": "Gibah; ime treh krajev v Palestini",
    "sv": "Gibah; namnet på tre platser i Palestina",
    "tr": "Gibah; Filistin'de üç yerin adı",
    "uk": "Гіба; назва трьох місць у Палестині",
    "zh": "吉巴；巴勒斯坦三个地名"
  },
  "hebrew": "גִּבְעָה",
  "verses": [
    "joshua 15:57:1",
    "judges 19:12:15",
    "judges 19:13:7",
    "judges 19:14:6",
    "judges 19:15:4",
    "judges 19:16:14",
    "judges 20:4:7",
    "judges 20:5:3",
    "judges 20:9:5",
    "judges 20:13:7",
    "judges 20:14:5",
    "judges 20:15:14",
    "judges 20:19:6",
    "judges 20:20:12",
    "judges 20:21:4",
    "judges 20:25:4",
    "judges 20:29:4",
    "judges 20:30:10",
    "judges 20:31:21",
    "judges 20:33:13",
    "judges 20:34:2",
    "judges 20:36:17",
    "judges 20:37:4",
    "judges 20:43:8",
    "firstSamuel 10:26:4",
    "firstSamuel 11:4:2",
    "firstSamuel 13:2:18",
    "firstSamuel 13:15:5",
    "firstSamuel 14:2:3",
    "firstSamuel 14:16:3",
    "firstSamuel 15:34:7",
    "firstSamuel 22:6:10",
    "firstSamuel 23:19:4",
    "firstSamuel 26:1:4",
    "secondSamuel 21:6:8",
    "secondSamuel 23:29:7",
    "firstChronicles 11:31:3",
    "secondChronicles 13:2:10",
    "isaiah 10:29:7",
    "hosea 5:8:2",
    "hosea 9:9:3",
    "hosea 10:9:1",
    "hosea 10:9:8"
  ]
}