{
  "number": "H1447",
  "language": "hebrew",
  "transliteration": "gâdêr",
  "pronunciation": "gaw-dare'",
  "definition": "a circumvallation; by implication, an inclosure",
  "kjvTranslation": "fence, hedge, wall.",
  "translations": {
    "bg": "обграждане; по подразбиране - заграждение",
    "cs": "obklopení; implicitně ohrazení",
    "da": "en omkreds; underforstået, en indhegning",
    "de": "eine Umzäunung; implizit auch eine Einfriedung",
    "el": "μια περίφραξη- κατ' επέκταση, μια περίφραξη",
    "es": "una circunvalación; implícitamente, un recinto cerrado",
    "et": "ümbermõõtmine; kaudselt ka ümbermõõtmine",
    "fi": "kehä; implisiittisesti myös aitaaminen",
    "fr": "une circonvallation ; par voie de conséquence, une enceinte",
    "hu": "körülkerítés; értelemszerűen egy bekerítés",
    "id": "sebuah pengelabuan; dengan implikasi, sebuah penutup",
    "it": "una circonvallazione; per implicazione, un'area chiusa",
    "ja": "円周; 暗黙のうちに、囲い",
    "ko": "우회; 암시적으로 인클로저를 의미합니다",
    "lt": "apsuptis; netiesiogiai - užtvara",
    "lv": "norobežojums; netieši - iežogojums",
    "nb": "en omkrets; underforstått, en innhegning",
    "nl": "een circumvallatie; bij implicatie, een omheining",
    "pl": "obwód; w domyśle, zamknięcie",
    "pt": "uma circunvalação; implicitamente, um recinto fechado",
    "ro": "o circumvalație; implicit, o înclinație",
    "ru": "окружность; по косвенным признакам - ограждение",
    "sk": "obkolesenie; implicitne aj ohradenie",
    "sl": "oboda; implicitno tudi ograja",
    "sv": "en omslutning; underförstått, en inneslutning",
    "tr": "bir çevre duvarı; ima yoluyla, bir çit",
    "uk": "обхідний шлях; непрямий натяк, включення",
    "zh": "环绕；暗示，围合"
  },
  "hebrew": "גָּדֵר",
  "verses": [
    "numbers 22:24:5",
    "numbers 22:24:7",
    "ezra 9:9:25",
    "psalms 62:4:9",
    "psalms 80:13:2",
    "ecclesiastes 10:8:5",
    "isaiah 5:5:14",
    "ezekiel 13:5:4",
    "ezekiel 22:30:4",
    "ezekiel 42:7:0",
    "micah 7:11:2"
  ]
}