{
  "number": "H197",
  "language": "hebrew",
  "transliteration": "ʼûwlâm",
  "pronunciation": "oo-lawm'",
  "definition": "a vestibule (as bound to the building)",
  "kjvTranslation": "porch.",
  "translations": {
    "bg": "преддверие (като връзка със сградата)",
    "cs": "vestibul (jako součást budovy)",
    "da": "en vestibule (som bindeled til bygningen)",
    "de": "ein Vestibül (als Verbindung zum Gebäude)",
    "el": "έναν προθάλαμο (που συνδέεται με το κτίριο)",
    "es": "un vestíbulo (unido al edificio)",
    "et": "vestibüül (hoonega seotud)",
    "fi": "eteinen (rakennukseen sidottuna)",
    "fr": "un vestibule (lié au bâtiment)",
    "hu": "előcsarnok (az épülethez kötve)",
    "id": "ruang depan (seperti terikat pada bangunan)",
    "it": "un vestibolo (legato all'edificio)",
    "ja": "前庭",
    "ko": "현관(건물에 묶여 있는 경우)",
    "lt": "vestibiulis (susietas su pastatu)",
    "lv": "vestibils (kā savienojums ar ēku)",
    "nb": "en vestibyle (som er knyttet til bygningen)",
    "nl": "een vestibule (als gebonden aan het gebouw)",
    "pl": "przedsionek (jako powiązany z budynkiem)",
    "pt": "um vestíbulo (ligado a um edifício)",
    "ro": "un vestibul (legat de clădire)",
    "ru": "вестибюль (как связанный со зданием)",
    "sk": "vestibul (ako spojenie s budovou)",
    "sl": "preddverje (kot povezava s stavbo)",
    "sv": "en vestibul (som är knuten till byggnaden)",
    "tr": "bir antre (binaya bağlı olarak)",
    "uk": "вестибюль (прив'язаний до будівлі)",
    "zh": "套间"
  },
  "hebrew": "אוּלָם",
  "verses": [
    "ezekiel 40:15",
    "ezekiel 40:39",
    "ezekiel 40:40",
    "ezekiel 40:48",
    "ezekiel 40:49",
    "ezekiel 40:7",
    "ezekiel 40:8",
    "ezekiel 40:9",
    "ezekiel 41:15",
    "ezekiel 41:25",
    "ezekiel 41:26",
    "ezekiel 44:3",
    "ezekiel 46:2",
    "ezekiel 46:8",
    "ezekiel 8:16",
    "firstChronicles 28:11",
    "firstKings 6:3",
    "firstKings 7:12",
    "firstKings 7:19",
    "firstKings 7:21",
    "firstKings 7:6",
    "firstKings 7:7",
    "firstKings 7:8",
    "joel 2:17",
    "secondChronicles 15:8",
    "secondChronicles 29:17",
    "secondChronicles 29:7",
    "secondChronicles 3:4",
    "secondChronicles 8:12"
  ]
}