{
  "number": "H2713",
  "language": "hebrew",
  "transliteration": "châqar",
  "pronunciation": "khaw-kar'",
  "definition": "properly, to penetrate; hence, to examine intimately",
  "kjvTranslation": "find out, (make) search (out), seek (out), sound, try.",
  "translations": {
    "bg": "правилно, да прониквам; следователно, да изследвам отблизо",
    "cs": "správně, proniknout, tedy důkladně prozkoumat",
    "da": "korrekt, at trænge ind; derfor at undersøge intimt",
    "de": "richtig: durchdringen; daher: eingehend untersuchen",
    "el": "σωστά, διεισδύω- ως εκ τούτου, εξετάζω διεξοδικά",
    "es": "propiamente, penetrar; por lo tanto, examinar íntimamente",
    "et": "õigesti, tungida; seega, uurida põhjalikult",
    "fi": "kunnolla, tunkeutua; siis tutkia läpikotaisin",
    "fr": "proprement dit, pénétrer ; par conséquent, examiner intimement",
    "hu": "megfelelően, behatolni; ezért alaposan megvizsgálni",
    "id": "dengan benar, untuk menembus; karenanya, untuk memeriksa secara mendalam",
    "it": "propriamente, penetrare; quindi, esaminare intimamente",
    "ja": "つまり、親密に調べることである。",
    "ko": "적절하게, 관통하다; 따라서 면밀히 조사하다",
    "lt": "tinkamai, įsiskverbti; taigi, nuodugniai ištirti",
    "lv": "pareizi - iedziļināties, tātad - rūpīgi izpētīt",
    "nb": "riktig, å trenge inn; derav, å undersøke intimt",
    "nl": "goed, doordringen; vandaar, grondig onderzoeken",
    "pl": "właściwie, przeniknąć; stąd, dogłębnie zbadać",
    "pt": "propriamente dito, penetrar; portanto, examinar intimamente",
    "ro": "corect, a pătrunde; prin urmare, a examina în profunzime",
    "ru": "правильно, проникать; следовательно, исследовать досконально",
    "sk": "správne, preniknúť; teda dôkladne preskúmať",
    "sl": "pravilno, prodreti; torej temeljito pregledati",
    "sv": "korrekt, att tränga igenom; följaktligen, att undersöka intimt",
    "tr": "uygun şekilde, nüfuz etmek; dolayısıyla, yakından incelemek",
    "uk": "власне, проникати; отже, уважно вивчати",
    "zh": "正确地说，是穿透；因此，是仔细检查"
  },
  "hebrew": "חָקַר",
  "verses": [
    "deuteronomy 13:15:1",
    "judges 18:2:15",
    "judges 18:2:19",
    "firstSamuel 20:12:8",
    "secondSamuel 10:3:18",
    "firstKings 7:47:9",
    "firstChronicles 19:3:16",
    "secondChronicles 4:18:9",
    "job 5:27:2",
    "job 13:9:2",
    "job 28:3:6",
    "job 28:27:5",
    "job 29:16:6",
    "job 32:11:7",
    "psalms 44:22:2",
    "psalms 139:1:4",
    "psalms 139:23:0",
    "proverbs 18:17:6",
    "proverbs 23:30:4",
    "proverbs 25:2:6",
    "proverbs 28:11:6",
    "ecclesiastes 12:9:10",
    "jeremiah 17:10:2",
    "jeremiah 31:37:7",
    "jeremiah 46:23:6",
    "lamentations 3:40:2",
    "ezekiel 39:14:17"
  ]
}