{
  "number": "H2741",
  "language": "hebrew",
  "transliteration": "Chărûwphîy",
  "pronunciation": "khar-oo-fee'",
  "definition": "a Charuphite or inhabitant of Charuph (or Chariph)",
  "kjvTranslation": "Haruphite.",
  "translations": {
    "bg": "харуфит или жител на Харуп (или Харип)",
    "cs": "charuphite nebo obyvatel Charuphu (nebo Chariphu)",
    "da": "en Charuphite eller indbygger i Charuph (eller Chariph)",
    "de": "ein Charuphite oder Einwohner von Charuph (oder Chariph)",
    "el": "charuphite ή κάτοικος του Charuph (ή Chariph)",
    "es": "un charuphita o habitante de Charuph (o Chariph)",
    "et": "charuph'i (või Chariph'i) elanik või Charuph'i (või Chariph'i) elanik",
    "fi": "charuphilainen tai Charuphin (tai Chariphin) asukas",
    "fr": "un Charuphite ou un habitant de Charuph (ou Chariph)",
    "hu": "charuph (vagy Chariph) lakója vagy Charuph (vagy Chariph) lakója",
    "id": "seorang Charuphite atau penduduk Charuph (atau Chariph)",
    "it": "un Charuphite o un abitante di Charuph (o Chariph)",
    "ja": "シャルフ人またはシャルフの住民",
    "ko": "차루파이트 또는 차루프(또는 차리프)의 거주자",
    "lt": "charuphite arba Charuph (arba Chariph) gyventojas",
    "lv": "charupietis vai Charuph (vai Chariph) iedzīvotājs",
    "nb": "en Charuphite eller innbygger i Charuph (eller Chariph)",
    "nl": "een Charuphiet of inwoner van Charuph (of Chariph)",
    "pl": "charuphite lub mieszkaniec Charuph (lub Chariph)",
    "pt": "um Charuphite ou habitante de Charuph (ou Chariph)",
    "ro": "un Charuphite sau locuitor din Charuph (sau Chariph)",
    "ru": "чаруфит или житель Чаруфа (или Харифа)",
    "sk": "charuphite alebo obyvateľ Charuphu (alebo Chariphu)",
    "sl": "charuphite ali prebivalec Charupha (ali Charipha)",
    "sv": "en Charuphite eller invånare i Charuph (eller Chariph)",
    "tr": "bir Charuphite ya da Charuph (ya da Chariph) sakini",
    "uk": "чаруфіт або житель Чаруфа (або Харіфа)",
    "zh": "夏鲁普人或夏鲁普居民"
  },
  "hebrew": "חֲרוּפִי",
  "verses": [
    "firstChronicles 12:6:5",
    "firstChronicles 12:6:6"
  ]
}