{
  "number": "H3303",
  "language": "hebrew",
  "transliteration": "yâpheh",
  "pronunciation": "yaw-feh'",
  "definition": "beautiful (literally or figuratively)",
  "kjvTranslation": "[phrase] beautiful, beauty, comely, fair(-est, one), [phrase] goodly, pleasant, well.",
  "translations": {
    "bg": "красив (буквално или преносно)",
    "cs": "krásný (doslova nebo obrazně)",
    "da": "smuk (bogstaveligt eller i overført betydning)",
    "de": "schön (wörtlich oder im übertragenen Sinne)",
    "el": "όμορφη (κυριολεκτικά ή μεταφορικά)",
    "es": "bello (literal o figuradamente)",
    "et": "ilus (sõna otseses või ülekantud tähenduses)",
    "fi": "kaunis (kirjaimellisesti tai kuvainnollisesti)",
    "fr": "belle (au sens propre comme au sens figuré)",
    "hu": "gyönyörű (szó szerint vagy átvitt értelemben)",
    "id": "cantik (secara harfiah atau kiasan)",
    "it": "bella (in senso letterale o figurato)",
    "ja": "うつくしい",
    "ko": "아름다운(문자 그대로 또는 비유적으로)",
    "lt": "gražus (tiesiogine ar perkeltine prasme)",
    "lv": "skaisti (burtiski vai pārnestā nozīmē)",
    "nb": "vakker (bokstavelig eller i overført betydning)",
    "nl": "mooi (letterlijk of figuurlijk)",
    "pl": "piękny (dosłownie lub w przenośni)",
    "pt": "belo (literal ou figurativamente)",
    "ro": "frumos (la propriu sau la figurat)",
    "ru": "красивый (в прямом или переносном смысле)",
    "sk": "krásny (doslova alebo obrazne)",
    "sl": "lep (dobesedno ali v prenesenem pomenu)",
    "sv": "vacker (bokstavligen eller bildligt talat)",
    "tr": "güzel (gerçek veya mecazi anlamda)",
    "uk": "красиві (в прямому чи переносному сенсі)",
    "zh": "美丽"
  }
}