{
  "number": "H3374",
  "language": "hebrew",
  "transliteration": "yirʼâh",
  "pronunciation": "yir-aw'",
  "definition": "fear (also used as infinitive); morally, reverence",
  "kjvTranslation": "[idiom] dreadful, [idiom] exceedingly, fear(-fulness).",
  "translations": {
    "bg": "страх (използва се и като инфинитив); в морален план - благоговение",
    "cs": "strach (používá se také jako infinitiv); morálně, úcta",
    "da": "frygt (også brugt som infinitiv); moralsk, ærbødighed",
    "de": "furcht (auch als Infinitiv verwendet); moralisch, Ehrfurcht",
    "el": "φόβος (χρησιμοποιείται επίσης ως απαρέμφατο)- ηθικά, σεβασμός",
    "es": "temor (también usado como infinitivo); moralmente, reverencia",
    "et": "hirm (kasutatakse ka infinitiivina); moraalselt, aukartus",
    "fi": "pelko (käytetään myös infinitiivinä); moraalisesti, kunnioitus",
    "fr": "peur (également utilisé comme infinitif) ; moralement, révérence",
    "hu": "félelem (főnévi igenévként is használatos); erkölcsileg, tisztelet",
    "id": "takut (juga digunakan sebagai infinitif); secara moral, penghormatan",
    "it": "timore (usato anche come infinitivo); moralmente, riverenza",
    "ja": "恐れ（不定詞としても使われる）；道徳的には、尊敬",
    "ko": "두려움(부정사로도 사용됨); 도덕적으로, 경외심",
    "lt": "baimė (taip pat vartojamas kaip infinityvas); moraliniu požiūriu - pagarba",
    "lv": "bailes (lietots arī kā nenoteiksme); morāli, godbijība",
    "nb": "frykt (også brukt som infinitiv); moralsk, ærbødighet",
    "nl": "vrees (ook gebruikt als infinitief); moreel, eerbied",
    "pl": "strach (używany również jako bezokolicznik); moralnie, szacunek",
    "pt": "medo (também usado como infinitivo); moralmente, reverência",
    "ro": "teamă (folosit și ca infinitiv); din punct de vedere moral, reverență",
    "ru": "страх (также используется как инфинитив); в моральном плане - благоговение",
    "sk": "strach (používa sa aj ako infinitív); morálne, úcta",
    "sl": "strah (uporablja se tudi kot nedoločnik); moralno, spoštovanje",
    "sv": "rädsla (används även som infinitiv); moraliskt, vördnad",
    "tr": "korku (mastar olarak da kullanılır); ahlaki olarak, hürmet",
    "uk": "страх (також вживається як інфінітив); морально, благоговіння",
    "zh": "敬畏"
  }
}