{
  "number": "H3510",
  "language": "hebrew",
  "transliteration": "kâʼab",
  "pronunciation": "kaw-ab'",
  "definition": "properly, to feel pain; by implication, to grieve; figuratively, to spoil",
  "kjvTranslation": "grieving, mar, have pain, make sad (sore), (be) sorrowful.",
  "translations": {
    "bg": "правилно, да изпитвам болка; косвено, да скърбя; преносно, да развалям",
    "cs": "správně, cítit bolest; implicitně, truchlit; přeneseně, kazit se",
    "da": "korrekt, at føle smerte; underforstået, at sørge; i overført betydning, at ødelægge",
    "de": "im eigentlichen Sinne: Schmerz empfinden; implizit: trauern; im übertragenen Sinne: verderben",
    "el": "σωστά, να αισθάνεστε πόνο- με την έννοια, να θλίβεστε- μεταφορικά, να χαλάτε",
    "es": "propiamente, sentir dolor; implícitamente, afligirse; figuradamente, echar a perder",
    "et": "õigesti, tunda valu; kaudselt, kurvastada; piltlikult, rikkuda",
    "fi": "oikein, tuntea kipua; implisiittisesti, surra; kuvaannollisesti, pilata",
    "fr": "au sens propre, ressentir de la douleur ; par implication, s'affliger ; au sens figuré, gâcher",
    "hu": "helyesen: fájdalmat érezni; értelemszerűen: bánkódni; átvitt értelemben: elrontani",
    "id": "secara benar, merasakan sakit; secara tersirat, berduka; secara kiasan, merusak",
    "it": "propriamente, provare dolore; per implicazione, addolorarsi; in senso figurato, rovinarsi",
    "ja": "比喩的には、台無しにする。",
    "ko": "제대로, 고통을 느끼다; 암시적으로, 슬퍼하다; 비유적으로, 망치다",
    "lt": "tinkamai - jausti skausmą; netiesiogiai - sielvartauti; perkeltine prasme - sugadinti",
    "lv": "pareizi - izjust sāpes; netieši - skumt; pārnestā nozīmē - sabojāt",
    "nb": "egentlig, å føle smerte; underforstått, å sørge; i overført betydning, å ødelegge",
    "nl": "op de juiste manier, pijn voelen; impliciet, treuren; figuurlijk, bederven",
    "pl": "właściwie, odczuwać ból; w domyśle, smucić się; w przenośni, psuć się",
    "pt": "propriamente dito, sentir dor; implicitamente, entristecer-se; figurativamente, estragar",
    "ro": "propriu-zis, a simți durere; implicit, a suferi; la figurat, a strica",
    "ru": "правильно, чувствовать боль; подразумевая, горевать; фигурально, портить",
    "sk": "správne, cítiť bolesť; implicitne, smútiť; obrazne, pokaziť",
    "sl": "pravilno, čutiti bolečino; implicitno, žalovati; v prenesenem pomenu, pokvariti",
    "sv": "korrekt, att känna smärta; underförstått, att sörja; bildligt, att förstöra",
    "tr": "uygun olarak, acı hissetmek; ima yoluyla, kederlenmek; mecazi olarak, şımarmak",
    "uk": "власне, відчувати біль; побічно, сумувати; образно, псувати",
    "zh": "剜肉、剜心、剜肺、剜肺、剜心、剜肺、剜心、剜肺"
  },
  "hebrew": "כָּאַב",
  "verses": [
    "genesis 34:25:4",
    "secondKings 3:19:18",
    "job 5:18:2",
    "job 14:22:3",
    "psalms 69:30:2",
    "proverbs 14:13:2",
    "ezekiel 13:22:7",
    "ezekiel 28:24:8"
  ]
}