{
  "number": "H5030",
  "language": "hebrew",
  "transliteration": "nâbîyʼ",
  "pronunciation": "naw-bee'",
  "definition": "a prophet or (generally) inspired man",
  "kjvTranslation": "prophecy, that prophesy, prophet.",
  "hebrew": "נָבִיא",
  "translations": {
    "bg": "пророк или (обикновено) вдъхновен човек",
    "cs": "prorok nebo (obecně) inspirovaný člověk",
    "da": "en profet eller (generelt) inspireret mand",
    "de": "ein Prophet oder (im Allgemeinen) inspirierter Mann",
    "el": "προφήτης ή (γενικά) εμπνευσμένος άνθρωπος",
    "es": "profeta u hombre (generalmente) inspirado",
    "et": "prohvet või (üldiselt) inspireeritud inimene",
    "fi": "profeetta tai (yleensä) inspiroitunut mies",
    "fr": "un prophète ou un homme (généralement) inspiré",
    "hu": "próféta vagy (általában) ihletett ember",
    "id": "seorang nabi atau orang yang (umumnya) diilhami",
    "it": "un profeta o un uomo (generalmente) ispirato",
    "ja": "預言者",
    "ko": "선지자 또는 (일반적으로) 영감을 받은 사람",
    "lt": "pranašas arba (paprastai) įkvėptas žmogus",
    "lv": "pravietis vai (parasti) iedvesmots cilvēks",
    "nb": "en profet eller (generelt) inspirert mann",
    "nl": "een profeet of (over het algemeen) geïnspireerde man",
    "pl": "prorok lub (ogólnie) natchniony człowiek",
    "pt": "um profeta ou homem (geralmente) inspirado",
    "ro": "un profet sau un om (în general) inspirat",
    "ru": "пророк или (как правило) вдохновенный человек",
    "sk": "prorok alebo (všeobecne) inšpirovaný človek",
    "sl": "prerok ali (splošno) navdihnjen človek",
    "sv": "en profet eller (allmänt) inspirerad man",
    "tr": "bir peygamber veya (genellikle) ilham almış bir adam",
    "uk": "пророк або (загалом) натхненна людина",
    "zh": "先知"
  },
  "verses": [
    "genesis 20:7:5",
    "exodus 7:1:11",
    "numbers 11:29:11",
    "numbers 12:6:6",
    "deuteronomy 13:2:3",
    "deuteronomy 13:4:4",
    "deuteronomy 13:6:0",
    "deuteronomy 18:15:0",
    "deuteronomy 18:18:0",
    "deuteronomy 18:20:1",
    "deuteronomy 18:20:18",
    "deuteronomy 18:22:2",
    "deuteronomy 18:22:18",
    "deuteronomy 34:10:2",
    "judges 6:8:3",
    "firstSamuel 3:20:10",
    "firstSamuel 9:9:13",
    "firstSamuel 10:5:15",
    "firstSamuel 10:10:5",
    "firstSamuel 10:11:8",
    "firstSamuel 10:11:22",
    "firstSamuel 10:12:12",
    "firstSamuel 19:20:9",
    "firstSamuel 19:24:21",
    "firstSamuel 22:5:2",
    "firstSamuel 28:6:11",
    "firstSamuel 28:15:24",
    "secondSamuel 7:2:4",
    "secondSamuel 12:25:3",
    "secondSamuel 24:11:8",
    "firstKings 1:8:6",
    "firstKings 1:10:2",
    "firstKings 1:22:6",
    "firstKings 1:23:5",
    "firstKings 1:32:8",
    "firstKings 1:34:6",
    "firstKings 1:38:4",
    "firstKings 1:44:8",
    "firstKings 1:45:5",
    "firstKings 11:29:10",
    "firstKings 13:11:0",
    "firstKings 13:18:4",
    "firstKings 13:20:9",
    "firstKings 13:23:9",
    "firstKings 13:25:17",
    "firstKings 13:26:1",
    "firstKings 13:29:1",
    "firstKings 13:29:13",
    "firstKings 14:2:18",
    "firstKings 14:18:13",
    "firstKings 16:7:5",
    "firstKings 16:12:14",
    "firstKings 18:4:4",
    "firstKings 18:4:9",
    "firstKings 18:13:9",
    "firstKings 18:13:12",
    "firstKings 18:19:11",
    "firstKings 18:19:16",
    "firstKings 18:20:7",
    "firstKings 18:22:6",
    "firstKings 18:22:9",
    "firstKings 18:25:2",
    "firstKings 18:36:5",
    "firstKings 18:40:5",
    "firstKings 19:1:14",
    "firstKings 19:10:15",
    "firstKings 19:14:15",
    "firstKings 19:16:15",
    "firstKings 20:13:1",
    "firstKings 20:22:1",
    "firstKings 20:35:3",
    "firstKings 20:38:1",
    "firstKings 20:41:12",
    "firstKings 22:6:4",
    "firstKings 22:7:4",
    "firstKings 22:10:16",
    "firstKings 22:12:1",
    "firstKings 22:13:11",
    "firstKings 22:22:7",
    "firstKings 22:23:8",
    "secondKings 2:3:2",
    "secondKings 2:5:2",
    "secondKings 2:7:3",
    "secondKings 2:15:2",
    "secondKings 3:11:4",
    "secondKings 3:13:10",
    "secondKings 3:13:13",
    "secondKings 4:1:4",
    "secondKings 4:38:6",
    "secondKings 4:38:17",
    "secondKings 5:3:6",
    "secondKings 5:8:24",
    "secondKings 5:13:8",
    "secondKings 5:22:15",
    "secondKings 6:1:2",
    "secondKings 6:12:8",
    "secondKings 9:1:1",
    "secondKings 9:1:5",
    "secondKings 9:4:3",
    "secondKings 9:7:8",
    "secondKings 10:19:2",
    "secondKings 14:25:21",
    "secondKings 17:13:6",
    "secondKings 17:13:7",
    "secondKings 17:13:28",
    "secondKings 17:23:13",
    "secondKings 19:2:15",
    "secondKings 20:1:10",
    "secondKings 20:11:2",
    "secondKings 20:14:2",
    "secondKings 21:10:4",
    "secondKings 23:2:12",
    "secondKings 23:18:11",
    "secondKings 24:2:25",
    "firstChronicles 16:22:3",
    "firstChronicles 17:1:9",
    "firstChronicles 25:1:9",
    "firstChronicles 29:29:14",
    "secondChronicles 9:29:11",
    "secondChronicles 12:5:1",
    "secondChronicles 12:15:9",
    "secondChronicles 13:22:7",
    "secondChronicles 15:8:6",
    "secondChronicles 18:5:4",
    "secondChronicles 18:6:4",
    "secondChronicles 18:9:17",
    "secondChronicles 18:11:1",
    "secondChronicles 18:12:10",
    "secondChronicles 18:21:7",
    "secondChronicles 18:22:7",
    "secondChronicles 20:20:18",
    "secondChronicles 21:12:4",
    "secondChronicles 24:19:2",
    "secondChronicles 25:15:6",
    "secondChronicles 25:16:13",
    "secondChronicles 26:22:9",
    "secondChronicles 28:9:2",
    "secondChronicles 29:25:14",
    "secondChronicles 29:25:20",
    "secondChronicles 32:20:6",
    "secondChronicles 32:32:10",
    "secondChronicles 35:18:7",
    "secondChronicles 36:12:9",
    "secondChronicles 36:16:7",
    "ezra 9:11:4",
    "nehemiah 6:7:1",
    "nehemiah 6:14:10",
    "nehemiah 9:26:9",
    "nehemiah 9:30:8",
    "nehemiah 9:32:20",
    "psalms 51:2:3",
    "psalms 74:9:5",
    "psalms 105:15:3",
    "isaiah 3:2:4",
    "isaiah 9:14:5",
    "isaiah 28:7:7",
    "isaiah 29:10:10",
    "isaiah 37:2:18",
    "isaiah 38:1:10",
    "isaiah 39:3:2",
    "jeremiah 1:5:9",
    "jeremiah 2:8:12",
    "jeremiah 2:26:12",
    "jeremiah 2:30:9",
    "jeremiah 4:9:12",
    "jeremiah 5:13:0",
    "jeremiah 5:31:0",
    "jeremiah 6:13:7",
    "jeremiah 7:25:15",
    "jeremiah 8:1:18",
    "jeremiah 8:10:14",
    "jeremiah 13:13:21",
    "jeremiah 14:13:5",
    "jeremiah 14:14:4",
    "jeremiah 14:15:5",
    "jeremiah 14:15:22",
    "jeremiah 14:18:14",
    "jeremiah 18:18:14",
    "jeremiah 20:2:4",
    "jeremiah 23:9:0",
    "jeremiah 23:11:2",
    "jeremiah 23:13:0",
    "jeremiah 23:14:0",
    "jeremiah 23:15:6",
    "jeremiah 23:15:16",
    "jeremiah 23:16:8",
    "jeremiah 23:21:3",
    "jeremiah 23:25:4",
    "jeremiah 23:26:4",
    "jeremiah 23:26:7",
    "jeremiah 23:28:0",
    "jeremiah 23:30:3",
    "jeremiah 23:31:2",
    "jeremiah 23:33:5",
    "jeremiah 23:34:0",
    "jeremiah 23:37:3",
    "jeremiah 25:2:3",
    "jeremiah 25:4:6",
    "jeremiah 26:5:4",
    "jeremiah 26:7:2",
    "jeremiah 26:8:16",
    "jeremiah 26:11:2",
    "jeremiah 26:16:7",
    "jeremiah 27:9:4",
    "jeremiah 27:14:4",
    "jeremiah 27:15:14",
    "jeremiah 27:16:15",
    "jeremiah 27:18:1",
    "jeremiah 28:1:18",
    "jeremiah 28:5:2",
    "jeremiah 28:5:5",
    "jeremiah 28:6:2",
    "jeremiah 28:8:0",
    "jeremiah 28:9:0",
    "jeremiah 28:9:6",
    "jeremiah 28:9:8",
    "jeremiah 28:10:2",
    "jeremiah 28:10:8",
    "jeremiah 28:11:25",
    "jeremiah 28:12:8",
    "jeremiah 28:12:14",
    "jeremiah 28:15:2",
    "jeremiah 28:15:5",
    "jeremiah 28:17:2",
    "jeremiah 29:1:6",
    "jeremiah 29:1:15",
    "jeremiah 29:8:10",
    "jeremiah 29:15:5",
    "jeremiah 29:19:13",
    "jeremiah 29:29:8",
    "jeremiah 32:2:8",
    "jeremiah 32:32:14",
    "jeremiah 34:6:2",
    "jeremiah 35:15:5",
    "jeremiah 36:8:8",
    "jeremiah 36:26:20",
    "jeremiah 37:2:13",
    "jeremiah 37:3:14",
    "jeremiah 37:6:5",
    "jeremiah 37:13:16",
    "jeremiah 37:19:2",
    "jeremiah 38:9:10",
    "jeremiah 38:10:15",
    "jeremiah 38:14:6",
    "jeremiah 42:2:3",
    "jeremiah 42:4:3",
    "jeremiah 43:6:25",
    "jeremiah 44:4:5",
    "jeremiah 45:1:4",
    "jeremiah 46:1:6",
    "jeremiah 46:13:6",
    "jeremiah 47:1:6",
    "jeremiah 49:34:6",
    "jeremiah 50:1:11",
    "jeremiah 51:59:4",
    "lamentations 2:9:12",
    "lamentations 2:14:0",
    "lamentations 2:20:17",
    "lamentations 4:13:1",
    "ezekiel 2:5:11",
    "ezekiel 7:26:10",
    "ezekiel 13:2:4",
    "ezekiel 13:2:8",
    "ezekiel 13:3:6",
    "ezekiel 13:4:2",
    "ezekiel 13:9:3",
    "ezekiel 13:16:0",
    "ezekiel 14:4:26",
    "ezekiel 14:7:22",
    "ezekiel 14:9:0",
    "ezekiel 14:9:9",
    "ezekiel 14:10:5",
    "ezekiel 22:25:1",
    "ezekiel 22:28:0",
    "ezekiel 33:33:5",
    "ezekiel 38:17:12",
    "daniel 9:2:15",
    "daniel 9:6:4",
    "daniel 9:10:12",
    "daniel 9:24:21",
    "hosea 4:5:4",
    "hosea 6:5:3",
    "hosea 9:7:9",
    "hosea 9:8:4",
    "hosea 12:11:2",
    "hosea 12:11:7",
    "hosea 12:14:0",
    "hosea 12:14:6",
    "amos 2:11:2",
    "amos 2:12:5",
    "amos 3:7:12",
    "amos 7:14:6",
    "amos 7:14:10",
    "micah 3:5:4",
    "micah 3:6:10",
    "micah 3:11:6",
    "habakkuk 1:1:4",
    "habakkuk 3:1:2",
    "zephaniah 3:4:0",
    "haggai 1:1:14",
    "haggai 1:3:5",
    "haggai 1:12:18",
    "haggai 2:1:9",
    "haggai 2:10:11",
    "zechariah 1:1:14",
    "zechariah 1:4:6",
    "zechariah 1:5:3",
    "zechariah 1:6:7",
    "zechariah 1:7:21",
    "zechariah 7:3:8",
    "zechariah 7:7:7",
    "zechariah 7:12:14",
    "zechariah 8:9:13",
    "zechariah 13:2:17",
    "zechariah 13:4:4",
    "zechariah 13:5:2",
    "malachi 3:23:6"
  ]
}