{
  "number": "H5281",
  "language": "hebrew",
  "transliteration": "Noʻŏmîy",
  "pronunciation": "no-om-ee'",
  "definition": "Noomi, an Israelitess",
  "kjvTranslation": "Naomi.",
  "hebrew": "נׇעֳמִי",
  "translations": {
    "bg": "Нуми, израилтянка",
    "cs": "Noomi, Izraelka",
    "da": "Noomi, en israelitinde",
    "de": "Noomi, eine Israelitin",
    "el": "Noomi, μια Ισραηλίτισσα",
    "es": "Noomi, una israelita",
    "et": "Noomi, iisraellanna",
    "fi": "Noomi, israelilaisnainen",
    "fr": "Noomi, une Israélite",
    "hu": "Noomi, egy izraelita nő",
    "id": "Noomi, seorang Israel",
    "it": "Noomi, una israelita",
    "ja": "イスラエル人女性、ノオミ",
    "ko": "이스라엘인 누미",
    "lt": "Noomi, izraelietė",
    "lv": "Noomi, izraēliete",
    "nb": "Noomi, en israelittinne",
    "nl": "Noomi, een Israëlitische",
    "pl": "Noomi, Izraelitka",
    "pt": "Noomi, uma israelita",
    "ro": "Noomi, o israelită",
    "ru": "Нуми, израильтянка",
    "sk": "Noomi, Izraelitka",
    "sl": "Noomi, Izraelka",
    "sv": "Noomi, en israelitinna",
    "tr": "Noomi, bir İsrailli kadın",
    "uk": "Нумі, ізраїльтянка",
    "zh": "诺米，一位以色列女性"
  },
  "verses": [
    "ruth 1:2:5",
    "ruth 1:3:3",
    "ruth 1:8:1",
    "ruth 1:11:1",
    "ruth 1:19:16",
    "ruth 1:20:5",
    "ruth 1:21:9",
    "ruth 1:22:1",
    "ruth 2:1:0",
    "ruth 2:2:4",
    "ruth 2:6:11",
    "ruth 2:20:1",
    "ruth 2:20:16",
    "ruth 2:22:1",
    "ruth 3:1:2",
    "ruth 4:3:8",
    "ruth 4:5:6",
    "ruth 4:9:20",
    "ruth 4:14:3",
    "ruth 4:16:1",
    "ruth 4:17:7"
  ]
}