{
  "number": "H6009",
  "language": "hebrew",
  "transliteration": "ʻâmaq",
  "pronunciation": "aw-mak'",
  "definition": "to be (causatively, make) deep (literally or figuratively)",
  "kjvTranslation": "(be, have, make, seek) deep(-ly), depth, be profound.",
  "hebrew": "עָמַק",
  "translations": {
    "bg": "да бъде (в причинно-следствена връзка, да бъде) дълбоко (буквално или преносно)",
    "cs": "být (příčinně, způsobit) hluboký (doslova nebo obrazně)",
    "da": "at være (kausalt, gøre) dyb (bogstaveligt eller i overført betydning)",
    "de": "tief sein (kausal, machen) (wörtlich oder bildlich)",
    "el": "να είναι (αιτιωδώς, να κάνει) βαθιά (κυριολεκτικά ή μεταφορικά)",
    "es": "ser (causativamente, hacer) profundo (literal o figuradamente)",
    "et": "olla (põhjuslikult, teha) sügavalt (sõna-sõnalt või ülekantud tähenduses)",
    "fi": "olla (kausatiivisesti, tehdä) syvä (kirjaimellisesti tai kuvaannollisesti)",
    "fr": "être (causalement, rendre) profond (au sens propre ou au sens figuré)",
    "hu": "mélyen (szó szerint vagy átvitt értelemben) lenni (ok-okozati összefüggésben, mélyre hatolni)",
    "id": "menjadi (secara kausal, membuat) dalam (secara harfiah atau kiasan)",
    "it": "essere (causalmente, rendere) profondo (letteralmente o figurativamente)",
    "ja": "を深くする。",
    "ko": "(인과적으로, 만들다) 깊다(문자적 또는 비 유적으로)",
    "lt": "būti (priežastingai, giliai) (tiesiogine ar perkeltine prasme)",
    "lv": "būt (cēloņsakarīgi, padarīt) dziļi (burtiski vai pārnestā nozīmē)",
    "nb": "å være (kausativt, gjøre) dyp (bokstavelig eller billedlig)",
    "nl": "diep zijn (causaal, diep maken) (letterlijk of figuurlijk)",
    "pl": "być (przyczynowo, czynić) głębokim (dosłownie lub w przenośni)",
    "pt": "ser (causativamente, fazer) profundo (literal ou figurativamente)",
    "ro": "a fi (cauzal, a face) adânc (la propriu sau la figurat)",
    "ru": "быть (причинно, делать) глубоким (в прямом или переносном смысле)",
    "sk": "byť (príčinne, príčinne) hlboký (doslovne alebo obrazne)",
    "sl": "biti (vzročno) globok (dobesedno ali v prenesenem pomenu)",
    "sv": "att vara (kausalt, göra) djup (bokstavligt eller bildligt)",
    "tr": "(nedensel olarak, yapmak) derin olmak (gerçek veya mecazi olarak)",
    "uk": "бути (причинно, робити) глибоким (у прямому чи переносному значенні)",
    "zh": "深藏不露"
  },
  "verses": [
    "psalms 92:6:5",
    "isaiah 7:11:6",
    "isaiah 29:15:1",
    "isaiah 30:33:9",
    "isaiah 31:6:2",
    "jeremiah 49:8:2",
    "jeremiah 49:30:3",
    "hosea 5:2:2",
    "hosea 9:9:0"
  ]
}