{
  "number": "H6172",
  "language": "hebrew",
  "transliteration": "ʻervâh",
  "pronunciation": "er-vaw'",
  "definition": "nudity, literally (especially the pudenda) or figuratively (disgrace, blemish)",
  "kjvTranslation": "nakedness, shame, unclean(-ness).",
  "hebrew": "עֶרְוָה",
  "translations": {
    "bg": "голота, буквално (особено пудендата) или в преносен смисъл (позор, недостатък)",
    "cs": "nahota, doslova (zejména pudenda) nebo obrazně (hanba, vada)",
    "da": "nøgenhed, bogstaveligt (især pudenda) eller i overført betydning (skændsel, plet)",
    "de": "nacktheit, wörtlich (vor allem die Pudenda) oder im übertragenen Sinne (Schande, Schandfleck)",
    "el": "γυμνότητα, κυριολεκτικά (ιδίως η αιδοία) ή μεταφορικά (ντροπή, ψεγάδι)",
    "es": "desnudez, literalmente (especialmente la pudenda) o en sentido figurado (deshonra, mancha)",
    "et": "alastio, sõna otseses mõttes (eriti alasti) või ülekantud tähenduses (häbi, plekk)",
    "fi": "alastomuus, kirjaimellisesti (erityisesti alastomuus) tai kuvaannollisesti (häpeä, kauneusvirhe)",
    "fr": "la nudité, au sens propre (surtout le pudenda) ou au sens figuré (disgrâce, tache)",
    "hu": "meztelenség, szó szerint (különösen a szeméremtest) vagy átvitt értelemben (szégyen, szégyenfolt)",
    "id": "ketelanjangan, secara harfiah (terutama pudenda) atau secara kiasan (aib, cela)",
    "it": "nudità, in senso letterale (soprattutto le pudenda) o figurato (disgrazia, macchia)",
    "ja": "裸体",
    "ko": "노출, 문자 그대로(특히 푸덴다) 또는 비유적으로(수치심, 흠)",
    "lt": "nuogumas tiesiogine prasme (ypač pudenda) arba perkeltine prasme (gėda, dėmė)",
    "lv": "kailums, burtiski (īpaši pudenda) vai pārnestā nozīmē (kauns, kauna traips)",
    "nb": "nakenhet, bokstavelig (spesielt pudenda) eller i overført betydning (skam, skamplett)",
    "nl": "naaktheid, letterlijk (vooral de pudenda) of figuurlijk (schande, smet)",
    "pl": "nagość, dosłownie (zwłaszcza pudenda) lub w przenośni (hańba, skaza)",
    "pt": "nudez, literalmente (especialmente a pudenda) ou figurativamente (desgraça, mancha)",
    "ro": "nuditate, la propriu (în special pudenda) sau la figurat (rușine, pată)",
    "ru": "нагота, буквально (особенно срам) или фигурально (позор, порок)",
    "sk": "nahota, doslovne (najmä pudenda) alebo obrazne (hanba, škvrna)",
    "sl": "golota, dobesedno (zlasti pudenda) ali v prenesenem pomenu (sramota, madež)",
    "sv": "nakenhet, bokstavligen (särskilt pudenda) eller bildligt (skamfläck, skamfläck)",
    "tr": "çıplaklık, gerçek anlamda (özellikle pudenda) veya mecazi anlamda (utanç, leke)",
    "uk": "оголеність, у прямому (особливо пуденда) чи переносному значенні (ганьба, пляма)",
    "zh": "裸体，字面意思（尤其是阴部）或比喻（耻辱、瑕疵）"
  },
  "verses": [
    "genesis 9:22:5",
    "genesis 9:23:13",
    "genesis 9:23:17",
    "genesis 42:9:13",
    "genesis 42:12:4",
    "exodus 20:26:8",
    "exodus 28:42:6",
    "leviticus 18:6:9",
    "leviticus 18:7:0",
    "leviticus 18:7:2",
    "leviticus 18:7:10",
    "leviticus 18:8:0",
    "leviticus 18:8:5",
    "leviticus 18:9:0",
    "leviticus 18:9:14",
    "leviticus 18:10:0",
    "leviticus 18:10:8",
    "leviticus 18:10:10",
    "leviticus 18:11:0",
    "leviticus 18:11:10",
    "leviticus 18:12:0",
    "leviticus 18:13:0",
    "leviticus 18:14:0",
    "leviticus 18:15:0",
    "leviticus 18:15:9",
    "leviticus 18:16:0",
    "leviticus 18:16:5",
    "leviticus 18:17:0",
    "leviticus 18:17:14",
    "leviticus 18:18:7",
    "leviticus 18:19:7",
    "leviticus 20:11:6",
    "leviticus 20:17:12",
    "leviticus 20:17:16",
    "leviticus 20:17:23",
    "leviticus 20:18:8",
    "leviticus 20:19:0",
    "leviticus 20:20:5",
    "leviticus 20:21:8",
    "deuteronomy 23:15:16",
    "deuteronomy 24:1:14",
    "firstSamuel 20:30:18",
    "isaiah 20:4:16",
    "isaiah 47:3:1",
    "lamentations 1:8:12",
    "ezekiel 16:8:11",
    "ezekiel 16:36:8",
    "ezekiel 16:37:22",
    "ezekiel 16:37:27",
    "ezekiel 22:10:0",
    "ezekiel 23:10:2",
    "ezekiel 23:18:4",
    "ezekiel 23:29:10",
    "hosea 2:11:12"
  ]
}