{
  "number": "H6883",
  "language": "hebrew",
  "transliteration": "tsâraʻath",
  "pronunciation": "tsaw-rah'-ath",
  "definition": "leprosy",
  "kjvTranslation": "leprosy.",
  "hebrew": "צָרַעַת",
  "translations": {
    "bg": "проказа",
    "cs": "lepra",
    "da": "spedalskhed",
    "de": "lepra",
    "el": "λέπρα",
    "es": "lepra",
    "et": "lepra",
    "fi": "lepra",
    "fr": "lèpre",
    "hu": "lepra",
    "id": "kusta",
    "it": "lebbra",
    "ja": "ハンセン病",
    "ko": "나병",
    "lt": "raupsai",
    "lv": "lepras",
    "nb": "spedalskhet",
    "nl": "lepra",
    "pl": "trąd",
    "pt": "lepra",
    "ro": "lepra",
    "ru": "проказа",
    "sk": "lepra",
    "sl": "gobavost",
    "sv": "spetälska",
    "tr": "cüzzam",
    "uk": "проказа",
    "zh": "麻疯"
  },
  "verses": [
    "leviticus 13:2:14",
    "leviticus 13:3:16",
    "leviticus 13:8:8",
    "leviticus 13:9:1",
    "leviticus 13:11:0",
    "leviticus 13:12:3",
    "leviticus 13:12:6",
    "leviticus 13:13:4",
    "leviticus 13:15:10",
    "leviticus 13:20:13",
    "leviticus 13:25:12",
    "leviticus 13:25:20",
    "leviticus 13:27:12",
    "leviticus 13:30:18",
    "leviticus 13:42:8",
    "leviticus 13:43:12",
    "leviticus 13:47:5",
    "leviticus 13:49:17",
    "leviticus 13:51:20",
    "leviticus 13:52:22",
    "leviticus 13:59:3",
    "leviticus 14:3:10",
    "leviticus 14:7:4",
    "leviticus 14:32:5",
    "leviticus 14:34:12",
    "leviticus 14:44:7",
    "leviticus 14:54:4",
    "leviticus 14:55:0",
    "leviticus 14:57:7",
    "deuteronomy 24:8:2",
    "secondKings 5:3:12",
    "secondKings 5:6:18",
    "secondKings 5:7:19",
    "secondKings 5:27:0",
    "secondChronicles 26:19:8"
  ]
}