{
  "number": "H7065",
  "language": "hebrew",
  "transliteration": "qânâʼ",
  "pronunciation": "kaw-naw'",
  "definition": "to be (causatively, make) zealous, i.e. (in a bad sense) jealous or envious",
  "kjvTranslation": "(be) envy(-ious), be (move to, provoke to) jealous(-y), [idiom] very, (be) zeal(-ous).",
  "hebrew": "קָנָא",
  "translations": {
    "bg": "да бъда (в причинно-следствено значение, да предизвиквам) ревност, т.е. (в лош смисъл) да завиждам или да завиждам",
    "cs": "být (kauzativně, způsobit) horlivý, tj. (ve špatném smyslu) žárlivý nebo závistivý",
    "da": "at være (kausativt, gøre) nidkær, dvs. (i en dårlig betydning) jaloux eller misundelig",
    "de": "eifersüchtig sein (ursächlich, machen), d.h. (im schlechten Sinne) eifersüchtig oder neidisch sein",
    "el": "να είμαι (αιτιατικά, να κάνω) ζηλιάρης, δηλαδή (με την κακή έννοια) ζηλιάρης ή ζηλιάρης",
    "es": "ser (causativamente, hacer) celoso, es decir (en el mal sentido) celoso o envidioso",
    "et": "olla (põhjuslikult, teha) innukas, s.t. (halvas mõttes) kade või armukade",
    "fi": "olla (kausatiivisesti, tehdä) kiivas, eli (huonossa mielessä) kateellinen tai mustasukkainen",
    "fr": "être (causativement, rendre) zélé, c'est-à-dire (dans le mauvais sens du terme) jaloux ou envieux",
    "hu": "buzgólkodni, azaz (rossz értelemben) féltékeny vagy irigy lenni (ok-okozati úton)",
    "id": "menjadi (secara kausal, membuat) bersemangat, yaitu (dalam arti yang buruk) cemburu atau iri hati",
    "it": "essere (causalmente, rendere) zelante, cioè (in senso negativo) geloso o invidioso",
    "ja": "嫉妬する、うらやましがる",
    "ko": "열광하다, 즉 (나쁜 의미에서) 질투하거나 시기하다",
    "lt": "būti (priežastingai, sukelti) uoliam, t. y. (blogąja prasme) pavydžiam arba pavydulingam",
    "lv": "būt (cēloņsakarīgi, padarīt) greizsirdīgam, t.i., (sliktā nozīmē) greizsirdīgam vai skaudīgam",
    "nb": "å være (kausativt, gjøre) nidkjær, dvs. (i negativ forstand) sjalu eller misunnelig",
    "nl": "ijverig zijn (causatief, ijverig maken), d.w.z. (in slechte zin) jaloers of afgunstig zijn",
    "pl": "być (przyczynowo, powodować) gorliwym, tj. (w złym znaczeniu) zazdrosnym lub zawistnym",
    "pt": "ser (causativamente, tornar) zeloso, ou seja, (no mau sentido) ciumento ou invejoso",
    "ro": "a fi (cauzal, a face) zelos, adică (în sens negativ) gelos sau invidios",
    "ru": "быть (каузативно, вызывать) ревнивым, т.е. (в плохом смысле) завидовать или ревновать",
    "sk": "byť (kauzatívne, spôsobiť) horlivý, t. j. (v zlom zmysle) žiarlivý alebo závistlivý",
    "sl": "biti (vzročno, narediti) ljubosumen, tj. (v slabem pomenu) ljubosumen ali zavisten",
    "sv": "vara (kausalt, göra) nitisk, dvs. (i dålig bemärkelse) svartsjuk eller avundsjuk",
    "tr": "(nedensel olarak, yapmak) kıskanç olmak, yani (kötü anlamda) kıskanç veya hasetçi olmak",
    "uk": "бути (причинно, робити) ревним, тобто (в поганому сенсі) ревнивим або заздрісним",
    "zh": "热心，即（在不好的意义上）嫉妒或羡慕"
  },
  "verses": [
    "genesis 26:14",
    "genesis 30:1",
    "genesis 37:11",
    "numbers 5:14",
    "numbers 5:30",
    "numbers 11:29",
    "numbers 25:11",
    "numbers 25:13",
    "deuteronomy 32:16",
    "deuteronomy 32:21",
    "secondSamuel 21:2",
    "firstKings 14:22",
    "firstKings 19:10",
    "firstKings 19:14",
    "psalms 37:1",
    "psalms 73:3",
    "psalms 78:58",
    "psalms 106:16",
    "proverbs 3:31",
    "proverbs 23:17",
    "proverbs 24:1",
    "proverbs 24:19",
    "isaiah 11:13",
    "ezekiel 31:9",
    "ezekiel 39:25",
    "joel 2:18",
    "zechariah 1:14",
    "zechariah 8:2"
  ]
}